Neuralint/__init__.py
Neuralint/endToEnd.py
Neuralint/grooveParser.py
Neuralint/mix_bugs_1.py
Neuralint/nodes_Keras.py
Neuralint/nodes_TF.py
Neuralint/parser_Keras.py
Neuralint/parser_TF.py
neuralint-0.0.5.dist-info/METADATA
neuralint-0.0.5.dist-info/WHEEL
neuralint-0.0.5.dist-info/top_level.txt
neuralint-0.0.5.dist-info/RECORD
