Metadata-Version: 2.1
Name: neuralint
Version: 0.0.5
Summary: Neuralint package
Home-page: UNKNOWN
Author: Poly
Author-email: <ghassendaoud99@gmail.com>
License: UNKNOWN
Keywords: python,cnn,test
Platform: UNKNOWN
Classifier: Development Status :: 1 - Planning
Classifier: Intended Audience :: Developers
Classifier: Programming Language :: Python :: 3
Classifier: Operating System :: Unix
Classifier: Operating System :: MacOS :: MacOS X
Classifier: Operating System :: Microsoft :: Windows
Requires-Dist: tensorflow (==1.15)
